datacleaner_ai/__init__.py
datacleaner_ai/cleaner.py
datacleaner_ai/detectors.py
datacleaner_ai/reports.py
datacleaner_ai/transformers.py
datacleaner_ai/utils.py
datacleanerx-0.2.1.dist-info/licenses/LICENSE
datacleanerx-0.2.1.dist-info/METADATA
datacleanerx-0.2.1.dist-info/WHEEL
datacleanerx-0.2.1.dist-info/top_level.txt
datacleanerx-0.2.1.dist-info/RECORD
