Metadata-Version: 2.4
Name: datacleanerx
Version: 0.2.1
Summary: Automated dataset cleaner for machine learning
Home-page: https://github.com/SatyamSingh8306/datacleanerx
Author: Satyam Singh
Author-email: satyamsingh7734@example.com
Classifier: Programming Language :: Python :: 3
Classifier: License :: OSI Approved :: MIT License
Classifier: Operating System :: OS Independent
Requires-Python: >=3.7
License-File: LICENSE
Requires-Dist: pandas>=1.3.0
Requires-Dist: numpy>=1.20.0
Requires-Dist: scikit-learn>=1.0.0
Dynamic: author
Dynamic: author-email
Dynamic: classifier
Dynamic: description
Dynamic: description-content-type
Dynamic: home-page
Dynamic: license-file
Dynamic: requires-dist
Dynamic: requires-python
Dynamic: summary
